simple_amqp/__init__.py
simple_amqp/actions.py
simple_amqp/asyncio.py
simple_amqp/base.py
simple_amqp/data.py
simple_amqp/gevent.py
simple_amqp/log.py
simple_amqp-0.2.6.dist-info/METADATA
simple_amqp-0.2.6.dist-info/RECORD
simple_amqp-0.2.6.dist-info/WHEEL
simple_amqp-0.2.6.dist-info/top_level.txt
