Metadata-Version: 2.1
Name: simple-amqp
Version: 0.2.6
Summary: Simple AMQP lib
Home-page: https://github.com/rudineirk/py-simple-amqp
Author: Rudinei Goi Roecker
Author-email: rudinei.roecker@gmail.com
License: MIT
Keywords: simple amqp
Platform: UNKNOWN
Classifier: Development Status :: 3 - Alpha
Classifier: Intended Audience :: Developers
Classifier: Topic :: Software Development :: Libraries :: Application Frameworks
Classifier: License :: OSI Approved :: MIT License
Classifier: Programming Language :: Python :: 3
Classifier: Programming Language :: Python :: 3.6
Provides-Extra: gevent
Provides-Extra: asyncio
Requires-Dist: pika (<0.11,>=0.10)
Provides-Extra: asyncio
Requires-Dist: aio-pika; extra == 'asyncio'
Provides-Extra: gevent
Requires-Dist: gevent; extra == 'gevent'
